setup.py
threadsafevariable/__init__.py
threadsafevariable.egg-info/PKG-INFO
threadsafevariable.egg-info/SOURCES.txt
threadsafevariable.egg-info/dependency_links.txt
threadsafevariable.egg-info/not-zip-safe
threadsafevariable.egg-info/top_level.txt